[
  {
    "line": 1,
    "elements": [
      {
        "line": 3,
        "name": "Successful search with Valid Credentials",
        "description": "",
        "id": "searchbox-action;successful-search-with-valid-credentials",
        "type": "scenario",
        "keyword": "Scenario",
        "steps": [
          {
            "result": {
              "status": "undefined"
            },
            "line": 6,
            "name": "User is on Home Page",
            "match": {},
            "keyword": "Given "
          },
          {
            "result": {
              "status": "undefined"
            },
            "line": 7,
            "name": "User Navigate to LogIn Page",
            "match": {},
            "keyword": "When "
          },
          {
            "result": {
              "status": "undefined"
            },
            "line": 8,
            "name": "User enters UserName and Password",
            "match": {},
            "keyword": "Then "
          }
        ]
      }
    ],
    "name": "SearchBox Action",
    "description": "",
    "id": "searchbox-action",
    "keyword": "Feature",
    "uri": "C:/Users/Sunzida/IdeaProjects/Cucu/src/test/java/feature/search.feature"
  }
]